openbk/__init__.py
openbk/statement/__init__.py
openbk/statement/flows.py
openbk/statement/transactions.py
openbk/utils/__init__.py
openbk/utils/categories.py
openbk/utils/exceptions.py
openbk/utils/extractors.py
openbk-1.0.1.data/data/openbk/awb.json
openbk-1.0.1.dist-info/COPYING
openbk-1.0.1.dist-info/METADATA
openbk-1.0.1.dist-info/WHEEL
openbk-1.0.1.dist-info/top_level.txt
openbk-1.0.1.dist-info/RECORD
