Metadata-Version: 2.1
Name: openbk
Version: 1.0.1
Summary: A python library to easily extract information and metrics from Moroccan bank statements.
Home-page: https://github.com/imadarchid/openbk
Author: Imad Archid
Author-email: hello@imadarchid.com
License: GPL
Requires-Python: >=3.10
License-File: COPYING
Requires-Dist: tabula-py
Requires-Dist: pandas
Requires-Dist: PyPDF2
